{
  "calibrated_al_fraction": 0.55,
  "calibration_scan": [
    {
      "x": 0.3,
      "E22_eV": 1.5975334153995044
    },
    {
      "x": 0.325,
      "E22_eV": 1.6048033260023757
    },
    {
      "x": 0.35,
      "E22_eV": 1.611738570489401
    },
    {
      "x": 0.375,
      "E22_eV": 1.6183579272254165
    },
    {
      "x": 0.4,
      "E22_eV": 1.6246783471367394
    },
    {
      "x": 0.425,
      "E22_eV": 1.630715374557303
    },
    {
      "x": 0.45,
      "E22_eV": 1.6364834417039829
    },
    {
      "x": 0.475,
      "E22_eV": 1.6419960648877772
    },
    {
      "x": 0.5,
      "E22_eV": 1.6472659626409298
    },
    {
      "x": 0.525,
      "E22_eV": 1.6523051085473872
    },
    {
      "x": 0.55,
      "E22_eV": 1.657124724324161
    },
    {
      "x": 0.575,
      "E22_eV": 1.6617352111162826
    },
    {
      "x": 0.6,
      "E22_eV": 1.6661460093347447
    }
  ],
  "variants": {
    "ideal": {
      "E11_eV": 1.4960008652645753,
      "E22_eV": 1.657124724324161,
      "delta_z_HH2_CB2_nm": 0.8283218453552266,
      "localization_claims": {
        "HH1_wide": true,
        "HH2_wide": false,
        "CB1_wide": true,
        "CB2_narrow": true
      },
      "well_character_HH2": {
        "energy_ordered_HH2_raw_index": 2,
        "energy_ordered_HH2_wide": 0.19245711066508314,
        "energy_ordered_HH2_narrow": 0.7284636860316756,
        "wide_localized_excited_HH_order": 4,
        "wide_localized_excited_HH_wide": 0.887850512132807
      },
      "zmel_e_nm": {
        "e1_z_e1": 21.71665054069747,
        "e1_z_e2": 0.9046885815190163,
        "e1_z_e3": -1.5744335392306104,
        "e2_z_e1": 0.9046885815190171,
        "e2_z_e2": 27.922290632378566,
        "e2_z_e3": 1.8327637725374768,
        "e3_z_e1": -1.57443353923061,
        "e3_z_e2": 1.8327637725374768,
        "e3_z_e3": 22.142309886741415
      },
      "zmel_hh_nm": {
        "hh1_z_hh1": 21.679341757009567,
        "hh1_z_hh2": 0.8066609363426755,
        "hh1_z_hh3": -1.33068601213326,
        "hh1_z_hh4": -0.0018429108803848725,
        "hh2_z_hh1": 0.8066609363426755,
        "hh2_z_hh2": 27.093968787023325,
        "hh2_z_hh3": 2.727949201013675,
        "hh2_z_hh4": 0.5329635749368418,
        "hh3_z_hh1": -1.33068601213326,
        "hh3_z_hh2": 2.727949201013675,
        "hh3_z_hh3": 23.043936732283907,
        "hh3_z_hh4": -1.6469398612964479,
        "hh4_z_hh1": -0.0018429108803848725,
        "hh4_z_hh2": 0.5329635749368434,
        "hh4_z_hh3": -1.6469398612964479,
        "hh4_z_hh4": 21.713634609558326
      },
      "interband_overlaps": {
        "hh1_e1": {
          "re": 0.859515114163002,
          "im": 0.0
        },
        "hh1_e2": {
          "re": -0.048198896698058304,
          "im": 0.0
        },
        "hh1_e3": {
          "re": -0.012410007181411803,
          "im": 0.0
        },
        "hh2_e1": {
          "re": 0.04115396292922084,
          "im": 0.0
        },
        "hh2_e2": {
          "re": 0.8352319129166954,
          "im": 0.0
        },
        "hh2_e3": {
          "re": -0.1627401633097262,
          "im": 0.0
        }
      },
      "computation_scheme": 0,
      "doping_max_cm3": 0.0
    },
    "graded": {
      "E11_eV": 1.4994065860981505,
      "E22_eV": 1.6736868282973147,
      "delta_z_HH2_CB2_nm": 3.348924134031382,
      "localization_claims": {
        "HH1_wide": true,
        "HH2_wide": true,
        "CB1_wide": true,
        "CB2_narrow": true
      },
      "well_character_HH2": {
        "energy_ordered_HH2_raw_index": 2,
        "energy_ordered_HH2_wide": 0.5820294577919969,
        "energy_ordered_HH2_narrow": 0.352164173150325,
        "wide_localized_excited_HH_order": 4,
        "wide_localized_excited_HH_wide": 0.8863323609540845
      },
      "zmel_e_nm": {
        "e1_z_e1": 21.767341340164265,
        "e1_z_e2": 0.9643783424795206,
        "e1_z_e3": -1.5039743192369621,
        "e2_z_e1": 0.9643783424795206,
        "e2_z_e2": 27.70306764860253,
        "e2_z_e3": 2.034058035710702,
        "e3_z_e1": -1.5039743192369626,
        "e3_z_e2": 2.034058035710702,
        "e3_z_e3": 22.357596514838296
      },
      "zmel_hh_nm": {
        "hh1_z_hh1": 21.716141466381874,
        "hh1_z_hh2": 1.2540036377813129,
        "hh1_z_hh3": -0.8518730871713572,
        "hh1_z_hh4": -0.003049807965065472,
        "hh2_z_hh1": 1.2540036377813129,
        "hh2_z_hh2": 24.35414351457115,
        "hh2_z_hh3": 3.268433465850673,
        "hh2_z_hh4": 1.1179405501694006,
        "hh3_z_hh1": -0.8518730871713572,
        "hh3_z_hh2": 3.268433465850673,
        "hh3_z_hh3": 25.7794609907479,
        "hh3_z_hh4": -1.301332691298857,
        "hh4_z_hh1": -0.003049807965065472,
        "hh4_z_hh2": 1.1179405501694006,
        "hh4_z_hh3": -1.301332691298857,
        "hh4_z_hh4": 21.815482970784018
      },
      "interband_overlaps": {
        "hh1_e1": {
          "re": 0.8589091305314813,
          "im": 0.0
        },
        "hh1_e2": {
          "re": -0.05109757825104947,
          "im": 0.0
        },
        "hh1_e3": {
          "re": -0.011689198279429464,
          "im": 0.0
        },
        "hh2_e1": {
          "re": 0.03391885206902269,
          "im": 0.0
        },
        "hh2_e2": {
          "re": 0.7095657616726565,
          "im": 0.0
        },
        "hh2_e3": {
          "re": -0.4635303970044108,
          "im": 0.0
        }
      },
      "computation_scheme": 0,
      "doping_max_cm3": 0.0
    }
  }
}